GLXViewer/__init__.py
GLXViewer/utils.py
GLXViewer/viewer.py
galaxie_viewer-0.0.1.dev24.dist-info/AUTHORS
galaxie_viewer-0.0.1.dev24.dist-info/LICENSE
galaxie_viewer-0.0.1.dev24.dist-info/METADATA
galaxie_viewer-0.0.1.dev24.dist-info/WHEEL
galaxie_viewer-0.0.1.dev24.dist-info/entry_points.txt
galaxie_viewer-0.0.1.dev24.dist-info/pbr.json
galaxie_viewer-0.0.1.dev24.dist-info/top_level.txt
galaxie_viewer-0.0.1.dev24.dist-info/RECORD
