Metadata-Version: 2.1
Name: galaxie-viewer
Version: 0.0.1.dev24
Summary: Python package to display text over text templates
Home-page: https://gitlab.com/Tuuux/galaxie-viewer
Author: Tuxa
Author-email: tuxa@rtnp.org
License: LGPLv3+
Keywords: gitlab
Platform: UNKNOWN
Classifier: Development Status :: 3 - Alpha
Classifier: Intended Audience :: Developers
Classifier: Intended Audience :: Science/Research
Classifier: Natural Language :: English
Classifier: License :: OSI Approved :: GNU General Public License v3 or later (GPLv3+)
Classifier: Programming Language :: Python
Classifier: Programming Language :: Python :: 3.7
Classifier: Topic :: Software Development :: Libraries
Classifier: Topic :: System :: System Shells
Classifier: Topic :: Text Processing :: Filters
Classifier: Topic :: Text Processing :: General
Requires-Python: >=3.7
Requires-Dist: wheel
Requires-Dist: green
